AUTHORS
Changelog
LICENSE
MANIFEST.in
README.rst
manage.py
setup.cfg
setup.py
docs/Makefile
docs/changelog.rst
docs/conf.py
docs/copyright.rst
docs/getting_started.rst
docs/glossary.rst
docs/index.rst
docs/injecting_metadata.rst
docs/make.bat
docs/_static/.keep
docs/_templates/.keep
docs/images/favicon.ico
docs/images/logo.png
docs/includes/installation.txt
docs/includes/introduction.txt
docs/reference/django_celery_results.backends.cache.rst
docs/reference/django_celery_results.backends.database.rst
docs/reference/django_celery_results.backends.rst
docs/reference/django_celery_results.managers.rst
docs/reference/django_celery_results.models.rst
docs/reference/django_celery_results.utils.rst
docs/reference/index.rst
docs/templates/readme.txt
patrowl_django_celery_results/__init__.py
patrowl_django_celery_results/admin.py
patrowl_django_celery_results/apps.py
patrowl_django_celery_results/managers.py
patrowl_django_celery_results/models.py
patrowl_django_celery_results/urls.py
patrowl_django_celery_results/utils.py
patrowl_django_celery_results/views.py
patrowl_django_celery_results.egg-info/PKG-INFO
patrowl_django_celery_results.egg-info/SOURCES.txt
patrowl_django_celery_results.egg-info/dependency_links.txt
patrowl_django_celery_results.egg-info/entry_points.txt
patrowl_django_celery_results.egg-info/not-zip-safe
patrowl_django_celery_results.egg-info/requires.txt
patrowl_django_celery_results.egg-info/top_level.txt
patrowl_django_celery_results/backends/__init__.py
patrowl_django_celery_results/backends/cache.py
patrowl_django_celery_results/backends/database.py
patrowl_django_celery_results/migrations/0001_initial.py
patrowl_django_celery_results/migrations/0002_add_task_name_args_kwargs.py
patrowl_django_celery_results/migrations/0003_auto_20181106_1101.py
patrowl_django_celery_results/migrations/0004_auto_20190516_0412.py
patrowl_django_celery_results/migrations/0005_taskresult_worker.py
patrowl_django_celery_results/migrations/0006_taskresult_date_created.py
patrowl_django_celery_results/migrations/0007_remove_taskresult_hidden.py
patrowl_django_celery_results/migrations/0008_chordcounter.py
patrowl_django_celery_results/migrations/0009_groupresult.py
patrowl_django_celery_results/migrations/0010_remove_duplicate_indices.py
patrowl_django_celery_results/migrations/0011_taskresult_periodic_task_name.py
