Metadata-Version: 2.1
Name: patrowl-django-celery-results
Version: 2.6.0
Summary: Celery result backends for Django.
Home-page: https://github.com/celery/django-celery-results
Author: Asif Saif Uddin, Ask Solem
Author-email: auvipy@gmail.com
License: BSD
Project-URL: Documentation, https://django-celery-results.readthedocs.io/en/latest/
Project-URL: Changelog, https://django-celery-results.readthedocs.io/en/latest/changelog.html
Project-URL: Repository, https://github.com/celery/django-celery-results
Keywords: celery django database result backend
Platform: any
Classifier: Development Status :: 5 - Production/Stable
Classifier: License :: OSI Approved :: BSD License
Classifier: Programming Language :: Python
Classifier: Programming Language :: Python :: 3
Classifier: Programming Language :: Python :: 3.7
Classifier: Programming Language :: Python :: 3.8
Classifier: Programming Language :: Python :: 3.9
Classifier: Programming Language :: Python :: 3.10
Classifier: Programming Language :: Python :: 3.11
Classifier: Programming Language :: Python :: Implementation :: CPython
Classifier: Programming Language :: Python :: Implementation :: PyPy
Classifier: Framework :: Django
Classifier: Framework :: Django :: 3.2
Classifier: Framework :: Django :: 4.0
Classifier: Framework :: Django :: 4.1
Classifier: Framework :: Django :: 4.2
Classifier: Framework :: Django :: 5.0
Classifier: Operating System :: OS Independent
Classifier: Topic :: Communications
Classifier: Topic :: System :: Distributed Computing
Classifier: Topic :: Software Development :: Libraries :: Python Modules
License-File: LICENSE
License-File: AUTHORS
